jactivecollab.py
jactivecollab-0.1.5.dist-info/METADATA
jactivecollab-0.1.5.dist-info/WHEEL
jactivecollab-0.1.5.dist-info/top_level.txt
jactivecollab-0.1.5.dist-info/RECORD
