Metadata-Version: 2.1
Name: jactivecollab
Version: 0.1.5
Summary: This package contains useful functions to extract data from Active Collab. It is designed for ETH juniors
Home-page: https://github.com/
Author: Frederik Semmel
Author-email: frederiksemmel@gmail.com
License: UNKNOWN
Platform: UNKNOWN
Classifier: Programming Language :: Python :: 3
Classifier: Programming Language :: Python :: 3.6
Classifier: License :: OSI Approved :: MIT License
Classifier: Operating System :: OS Independent
Requires-Python: >=3.6
Requires-Dist: requests (>=2.22.0)
Requires-Dist: numpy (>=1.18.0)
Requires-Dist: pandas (>=1.0)
Requires-Dist: mysql-connector-python (>=8.0)
